pyunitconverter/__init__.py
pyunitconverter/acceleration/__init__.py
pyunitconverter/acceleration/constants.py
pyunitconverter/energy/__init__.py
pyunitconverter/energy/constants.py
pyunitconverter/energy/converters.py
pyunitconverter/length/__init__.py
pyunitconverter/length/constants.py
pyunitconverter/length/converters.py
pyunitconverter/mass/__init__.py
pyunitconverter/mass/constants.py
pyunitconverter/mass/converters.py
pyunitconverter/prefixes/__init__.py
pyunitconverter/pressure/__init__.py
pyunitconverter/pressure/constants.py
pyunitconverter/speed/__init__.py
pyunitconverter/speed/constants.py
pyunitconverter/speed/converters.py
pyunitconverter/temperature/__init__.py
pyunitconverter/temperature/constants.py
pyunitconverter/temperature/converters.py
pyunitconverter/time/__init__.py
pyunitconverter/time/constants.py
pyunitconverter/time/converters.py
pyunitconverter/volume/__init__.py
pyunitconverter/volume/constants.py
pyunitconverter/volume/converters.py
pyunitconverter-0.5.1.dist-info/METADATA
pyunitconverter-0.5.1.dist-info/WHEEL
pyunitconverter-0.5.1.dist-info/RECORD
