Metadata-Version: 2.1
Name: pyunitconverter
Version: 0.5.1
Summary: Library of Python functions to converts units
Home-page: https://github.com/sdejongh/pyunitconverter
License: MIT
Keywords: units,conversion,helper
Author: Steve De Jongh
Author-email: dejongh.st@gmail.com
Requires-Python: >=3.9,<4.0
Classifier: Development Status :: 4 - Beta
Classifier: License :: OSI Approved :: MIT License
Classifier: Programming Language :: Python :: 3
Classifier: Programming Language :: Python :: 3.9
Classifier: Programming Language :: Python :: 3.10
Classifier: Programming Language :: Python :: 3.11
Classifier: Programming Language :: Python :: 3.12
Classifier: Topic :: Utilities
Project-URL: Bug Tracker, https://github.com/sdejongh/pyunitconverter/issues
Project-URL: Repository, https://github.com/sdejongh/pyunitconverter
